LICENSE
MANIFEST.in
README.md
pyproject.toml
setup.cfg
setup.py
django_quickmigrate.egg-info/PKG-INFO
django_quickmigrate.egg-info/SOURCES.txt
django_quickmigrate.egg-info/dependency_links.txt
django_quickmigrate.egg-info/top_level.txt
quickmigrate/__init__.py
quickmigrate/apps.py
quickmigrate/management/__init__.py
quickmigrate/management/commands/__init__.py
quickmigrate/management/commands/quickmigrate.py